Códigos alarmas/alarmas.v
//Universidad del Valle de Guatemala
//Gerardo Fuentes
//19389

//POS GATE LEVEL MODELLING: ALARMAS

module posSTL(input wire A, B, C, output wire Y1);

  wire c1, c2, c3, c4, c5, nelA, nelB, nelC;

  not (nelC, C);
  not (nelB, B);
  not (nelA, A);
  or  (c1, A, B, C);
  or  (c2, A, B, nelC);
  or  (c3, A, nelB, C);
  or  (c4, A, nelB, nelC);
  or  (c5, nelA, B, nelC);
  and (Y1, c1, c2, c3, c4, c5);

endmodule

//SOP GATE LEVEL MODELLING: ALARMAS

module sopSTL(input wire A, B, C, output wire Y2);

  wire w1, w2, w3, nB, nC;

  not (nB, B);
  not (nC, C);
  and (w1, A, nB, nC);
  and (w2, A, B, nC);
  and (w3, A, B, C);
  or  (Y2, w1, w2, w3);

endmodule

//MINIMIZADA GATE LEVEL MODELLING: ALARMAS

module mmzSTL(input wire A, B, C, output wire Y3);

  wire x1, x2, noC;

  not (noC, C);
  and (x1, A, noC);
  and (x2, A, B);
  or  (Y3, x1, x2);

endmodule

//POS BEHAVIORAL MODELLING: ALARMAS

module posBVL(input wire A, B, C, output wire Y4);

  assign Y4 = (A | B | C) & (A | B | ~C) & (A | ~B | C) & (A | ~B | ~C) & (~A | B | ~C);

endmodule

//SOP BEHAVIORAL MODELLING: ALARMAS

module sopBVL(input wire A, B, C, output wire Y5);

  assign Y5 = (A & ~B & ~C) | (A & B & ~C) | (A & B & C);

endmodule

//MINIMIZADA BEHAVIORAL MODELLING: ALARMAS

module mmzBVL(input wire A, B, C, output wire Y6);

  assign Y6 = (A & ~C) | (A & B);

endmodule

Códigos alarmas/alarmas_tb.v
//Universidad del Valle de Guatemala
//Gerardo Fuentes
// 19389

module testbench();

  reg t1, t2, t3;
  wire s1, s2, s3, s4, s5, s6;

  posSTL L1(t1, t2, t3, s1);
  sopSTL L2(t1, t2, t3, s2);
  mmzSTL L3(t1, t2, t3, s3);
  posBVL L4(t1, t2, t3, s4);
  sopBVL L5(t1, t2, t3, s5);
  mmzBVL L6(t1, t2, t3, s6);

  initial begin
    #1
    $display("\n");
    $display("Todas las ecuaciones");
    $display("A B C | Y1 Y2 Y3 Y4 Y5 Y6");
    $display("------|------------------");
    $monitor("%b %b %b | %b  %b  %b  %b  %b  %b", t1, t2, t3, s1, s2, s3, s4 ,s5, s6);
       t1 = 0; t2 = 0; t3 = 0;
    #1 t1 = 0; t2 = 0; t3 = 1;
    #1 t1 = 0; t2 = 1; t3 = 0;
    #1 t1 = 0; t2 = 1; t3 = 1;
    #1 t1 = 1; t2 = 0; t3 = 0;
    #1 t1 = 1; t2 = 0; t3 = 1;
    #1 t1 = 1; t2 = 1; t3 = 0;
    #1 t1 = 1; t2 = 1; t3 = 1;
  end

  initial
    #20 $finish;

  initial begin
    $dumpfile("alarmas_tb.vcd");
    $dumpvars(0, testbench);
  end

endmodule

Códigos alarmas/alarmas_tb.vcd
$date
	Sun Aug 09 02:15:06 2020
$end
$version
	Icarus Verilog
$end
$timescale
	1ps
$end
$scope module testbench $end
$var wire 1 ! s6 $end
$var wire 1 " s5 $end
$var wire 1 # s4 $end
$var wire 1 $ s3 $end
$var wire 1 % s2 $end
$var wire 1 & s1 $end
$var reg 1 ' t1 $end
$var reg 1 ( t2 $end
$var reg 1 ) t3 $end
$scope module L1 $end
$var wire 1 ' A $end
$var wire 1 ( B $end
$var wire 1 ) C $end
$var wire 1 & Y1 $end
$var wire 1 * c1 $end
$var wire 1 + c2 $end
$var wire 1 , c3 $end
$var wire 1 - c4 $end
$var wire 1 . c5 $end
$var wire 1 / nelA $end
$var wire 1 0 nelB $end
$var wire 1 1 nelC $end
$upscope $end
$scope module L2 $end
$var wire 1 ' A $end
$var wire 1 ( B $end
$var wire 1 ) C $end
$var wire 1 % Y2 $end
$var wire 1 2 nB $end
$var wire 1 3 nC $end
$var wire 1 4 w1 $end
$var wire 1 5 w2 $end
$var wire 1 6 w3 $end
$upscope $end
$scope module L3 $end
$var wire 1 ' A $end
$var wire 1 ( B $end
$var wire 1 ) C $end
$var wire 1 $ Y3 $end
$var wire 1 7 noC $end
$var wire 1 8 x1 $end
$var wire 1 9 x2 $end
$upscope $end
$scope module L4 $end
$var wire 1 ' A $end
$var wire 1 ( B $end
$var wire 1 ) C $end
$var wire 1 # Y4 $end
$upscope $end
$scope module L5 $end
$var wire 1 ' A $end
$var wire 1 ( B $end
$var wire 1 ) C $end
$var wire 1 " Y5 $end
$upscope $end
$scope module L6 $end
$var wire 1 ' A $end
$var wire 1 ( B $end
$var wire 1 ) C $end
$var wire 1 ! Y6 $end
$upscope $end
$upscope $end
$enddefinitions $end
#0
$dumpvars
x9
x8
x7
x6
x5
x4
x3
x2
x1
x0
x/
x.
x-
x,
x+
x*
x)
x(
x'
x&
x%
x$
x#
x"
x!
$end
#1
0#
0"
0&
1+
1,
1-
0%
0$
0!
11
13
17
10
1.
12
1/
0*
04
05
06
08
09
0)
0(
0'
#2
0&
0+
01
1*
03
07
1)
#3
11
0,
13
17
00
1+
02
0)
1(
#4
0&
0-
01
1,
03
07
1)
#5
1&
1"
1#
1$
1!
1%
18
14
11
13
17
10
1.
12
0/
1-
0)
0(
1'
#6
0&
0"
0%
0$
0#
0!
0.
04
08
01
03
07
1)
#7
1"
1%
1&
1#
15
18
1$
1!
11
13
17
00
1.
02
19
0)
1(
#8
05
08
01
03
16
07
1)
