Código/plab4.v
//Universidad del Valle de Guatemala
//Gerardo Fuentes
//19389

//Ejercicio 1.1

module ejer1(input wire A, B, C, output wire Y1);

  assign Y1 = (~A & ~C) | (A & C) | (A & ~B);

endmodule

//Ejercicio 1.2

module ejer2(input wire A, B, C, output wire Y2);

  not (Y2, B);

endmodule

//Ejercicio 1.3

module ejer3(input wire A, B, C, D, output wire Y3);

  assign Y3 = (~A & ~B & ~C & ~D) | (~A & ~B & C & D) | (~A & B & ~C & D) | (~A & B & C & ~D) | (A & B & ~C & ~D) | (A & B & C & D) | (A & ~B & ~C & D) | (A & ~B & C & ~D);

endmodule

//Ejercicio 1.4

module ejer4(input wire A, B, C, D, output wire Y4);

  assign Y4 = (B & D) | (A & C) | (~B & ~D) | (A & B);

endmodule

//Ejercicio 2.1

module ejer5(input wire A, B, C, D, output wire Y5);

  assign Y5 = (A & ~C) | (A & ~B) | (A & ~D) | (~B & ~C & ~D);

endmodule

//Ejercicio 2.2

module ejer6(input wire A, B, C, output wire Y6);

  wire nelB;

  not (nelB, B);
  or (Y6, nelB, C);

endmodule

//Ejercicio 2.3

module ejer7(input wire A, B, C, D, output wire Y7);

  wire w1, w2, nelC;

  not (nelC, C);
  and (w1, A, D);
  and (w2, nelC, D);
  or  (Y7, B, w1, w2);

endmodule

//Ejercicio 2.4

module ejer8(input wire A, B, C, output wire Y8);

  wire c1, nA, nC;
  not (nA, A);
  not (nC, C);
  and (c1, nA, nC);
  or  (Y8, c1, B);

endmodule

Código/plab4_tb.v
//Universidad del Valle de Guatemala
//Gerardo Fuentes
//19389

module testbench();

  reg b1, b2, b3, b4;
  wire s1, s2, s3, s4, s5, s6, s7, s8;

  ejer1 E1(b1, b2, b3, s1);
  ejer2 E2(b1, b2, b3, s2);
  ejer3 E3(b1, b2, b3, b4, s3);
  ejer4 E4(b1, b2, b3, b4, s4);
  ejer5 E5(b1, b2, b3, b4, s5);
  ejer6 E6(b1, b2, b3, s6);
  ejer7 E7(b1, b2, b3, b4, s7);
  ejer8 E8(b1, b2, b3, s8);

  initial begin
    #1
    $display("\n");
    $display("Tablas 1.1, 1.2, 2.2 y 2.4");
    $display("A B C | Y1 Y2 Y6 Y8");
    $display("------|------");
    $monitor("%b %b %b | %b %b %b %b", b1, b2, b3, s1, s2, s6, s8);
       b1 = 0; b2 = 0; b3 = 0;
    #1 b1 = 0; b2 = 0; b3 = 1;
    #1 b1 = 0; b2 = 1; b3 = 0;
    #1 b1 = 0; b2 = 1; b3 = 1;
    #1 b1 = 1; b2 = 0; b3 = 0;
    #1 b1 = 1; b2 = 0; b3 = 1;
    #1 b1 = 1; b2 = 1; b3 = 0;
    #1 b1 = 1; b2 = 1; b3 = 1;
  end

  initial begin
    #9
    $display("\n");
    $display("Tablas 1.3, 1.4, 2.1, 2.3");
    $display("A B C D | Y3 Y4 Y5 Y7");
    $display("--------|------------");
    $monitor("%b %b %b %b | %b %b %b %b", b1, b2, b3, b4, s3, s4, s5, s7);
       b1 = 0; b2 = 0; b3 = 0; b4 = 0;
    #1 b1 = 0; b2 = 0; b3 = 0; b4 = 1;
    #1 b1 = 0; b2 = 0; b3 = 1; b4 = 0;
    #1 b1 = 0; b2 = 0; b3 = 1; b4 = 1;
    #1 b1 = 0; b2 = 1; b3 = 0; b4 = 0;
    #1 b1 = 0; b2 = 1; b3 = 0; b4 = 1;
    #1 b1 = 0; b2 = 1; b3 = 1; b4 = 0;
    #1 b1 = 0; b2 = 1; b3 = 1; b4 = 1;
    #1 b1 = 1; b2 = 0; b3 = 0; b4 = 0;
    #1 b1 = 1; b2 = 0; b3 = 0; b4 = 1;
    #1 b1 = 1; b2 = 0; b3 = 1; b4 = 0;
    #1 b1 = 1; b2 = 0; b3 = 1; b4 = 1;
    #1 b1 = 1; b2 = 1; b3 = 0; b4 = 0;
    #1 b1 = 1; b2 = 1; b3 = 0; b4 = 1;
    #1 b1 = 1; b2 = 1; b3 = 1; b4 = 0;
    #1 b1 = 1; b2 = 1; b3 = 1; b4 = 1;
  end

  initial
    #30 $finish;

  initial begin
    $dumpfile("plab4_tb.vcd");
    $dumpvars(0, testbench);
  end

endmodule

Código/plab4_tb.vcd
$date
	Sun Aug 09 01:04:11 2020
$end
$version
	Icarus Verilog
$end
$timescale
	1ps
$end
$scope module testbench $end
$var wire 1 ! s8 $end
$var wire 1 " s7 $end
$var wire 1 # s6 $end
$var wire 1 $ s5 $end
$var wire 1 % s4 $end
$var wire 1 & s3 $end
$var wire 1 ' s2 $end
$var wire 1 ( s1 $end
$var reg 1 ) b1 $end
$var reg 1 * b2 $end
$var reg 1 + b3 $end
$var reg 1 , b4 $end
$scope module E1 $end
$var wire 1 ) A $end
$var wire 1 * B $end
$var wire 1 + C $end
$var wire 1 ( Y1 $end
$upscope $end
$scope module E2 $end
$var wire 1 ) A $end
$var wire 1 * B $end
$var wire 1 + C $end
$var wire 1 ' Y2 $end
$upscope $end
$scope module E3 $end
$var wire 1 ) A $end
$var wire 1 * B $end
$var wire 1 + C $end
$var wire 1 , D $end
$var wire 1 & Y3 $end
$upscope $end
$scope module E4 $end
$var wire 1 ) A $end
$var wire 1 * B $end
$var wire 1 + C $end
$var wire 1 , D $end
$var wire 1 % Y4 $end
$upscope $end
$scope module E5 $end
$var wire 1 ) A $end
$var wire 1 * B $end
$var wire 1 + C $end
$var wire 1 , D $end
$var wire 1 $ Y5 $end
$upscope $end
$scope module E6 $end
$var wire 1 ) A $end
$var wire 1 * B $end
$var wire 1 + C $end
$var wire 1 # Y6 $end
$var wire 1 - nelB $end
$upscope $end
$scope module E7 $end
$var wire 1 ) A $end
$var wire 1 * B $end
$var wire 1 + C $end
$var wire 1 , D $end
$var wire 1 " Y7 $end
$var wire 1 . nelC $end
$var wire 1 / w1 $end
$var wire 1 0 w2 $end
$upscope $end
$scope module E8 $end
$var wire 1 ) A $end
$var wire 1 * B $end
$var wire 1 + C $end
$var wire 1 ! Y8 $end
$var wire 1 1 c1 $end
$var wire 1 2 nA $end
$var wire 1 3 nC $end
$upscope $end
$upscope $end
$enddefinitions $end
#0
$dumpvars
x3
x2
x1
x0
x/
x.
x-
x,
x+
x*
x)
x(
x'
x&
x%
x$
x#
x"
x!
$end
#1
1(
1!
11
1#
1.
13
1'
1-
0/
12
0+
0*
0)
#2
0(
0$
0"
0!
00
01
0.
03
1+
#3
1(
x0
11
0#
1.
13
0'
0-
1"
1!
0+
1*
#4
0(
00
01
1#
0.
03
1+
#5
1(
1$
x0
1.
13
1'
1-
x"
0!
x/
02
0+
0*
1)
#6
1%
00
0.
03
1+
#7
x&
0(
x0
0#
1.
13
0'
0-
1"
1!
0+
1*
#8
x$
1(
00
1#
0.
03
1+
#9
1&
1(
1$
11
1.
13
1'
1-
0"
1!
0/
12
0,
0+
0*
0)
#10
0&
0%
0$
1"
10
1,
#11
1%
0(
0!
0"
01
00
0.
03
0,
1+
#12
1&
0%
1,
#13
0&
1(
11
0#
1.
13
0'
0-
1"
1!
0,
0+
1*
#14
1&
1%
10
1,
#15
0%
0(
01
00
1#
0.
03
0,
1+
#16
0&
1%
1,
#17
1$
1(
1.
13
1'
1-
0"
0!
02
0,
0+
0*
1)
#18
0%
1&
1"
1/
10
1,
#19
1%
0"
0/
00
0.
03
0,
1+
#20
0&
1"
1/
1,
#21
1&
0(
0/
0#
1.
13
0'
0-
1!
0,
0+
1*
#22
0&
1/
10
1,
#23
1(
0/
00
1#
0.
03
0,
1+
#24
1&
0$
1/
1,
